{
  "arch": "x86_64",
  "build": "0",
  "build_number": 0,
  "channel": "https://repo.anaconda.com/pkgs/main/win-64",
  "constrains": [],
  "depends": [],
  "extracted_package_dir": "D:\\Users\\MengLingjun\\Anaconda3\\pkgs\\ca-certificates-2018.03.07-0",
  "features": "",
  "files": [
    "Library/ssl/cacert.pem",
    "Library/ssl/cert.pem"
  ],
  "fn": "ca-certificates-2018.03.07-0.tar.bz2",
  "license": "ISC",
  "link": {
    "source": "D:\\Users\\MengLingjun\\Anaconda3\\pkgs\\ca-certificates-2018.03.07-0",
    "type": 1
  },
  "md5": "df2f346c2e8351372e6935ae6654da75",
  "name": "ca-certificates",
  "package_tarball_full_path": "D:\\Users\\MengLingjun\\Anaconda3\\pkgs\\ca-certificates-2018.03.07-0.tar.bz2",
  "paths_data": {
    "paths": [
      {
        "_path": "Library/ssl/cacert.pem",
        "path_type": "hardlink",
        "sha256": "79ea479e9f329de7075c40154c591b51eb056d458bc4dff76d9a4b9c6c4f6d0b",
        "sha256_in_prefix": "79ea479e9f329de7075c40154c591b51eb056d458bc4dff76d9a4b9c6c4f6d0b",
        "size_in_bytes": 215556
      },
      {
        "_path": "Library/ssl/cert.pem",
        "path_type": "hardlink",
        "sha256": "79ea479e9f329de7075c40154c591b51eb056d458bc4dff76d9a4b9c6c4f6d0b",
        "sha256_in_prefix": "79ea479e9f329de7075c40154c591b51eb056d458bc4dff76d9a4b9c6c4f6d0b",
        "size_in_bytes": 215556
      }
    ],
    "paths_version": 1
  },
  "platform": "win32",
  "requested_spec": "None",
  "size": 159120,
  "subdir": "win-64",
  "timestamp": 1522697555946,
  "track_features": "",
  "url": "https://repo.anaconda.com/pkgs/main/win-64/ca-certificates-2018.03.07-0.tar.bz2",
  "version": "2018.03.07"
}